agc_optims/__init__.py
agc_optims/utils.py
agc_optims/clipper/__init__.py
agc_optims/clipper/agc.py
agc_optims/optim/__init__.py
agc_optims/optim/adam_agc.py
agc_optims/optim/adamw_agc.py
agc_optims/optim/rmsprop_agc.py
agc_optims/optim/sgd_agc.py
agc_optims-0.0.2.dist-info/LICENSE
agc_optims-0.0.2.dist-info/METADATA
agc_optims-0.0.2.dist-info/WHEEL
agc_optims-0.0.2.dist-info/top_level.txt
agc_optims-0.0.2.dist-info/RECORD
