Metadata-Version: 2.1
Name: agc-optims
Version: 0.0.2
Summary: Easy to use optimizers with adaptive gradient clipping. Written in PyTorch.
Home-page: https://github.com/Skyy93/agc_optims
Author: Fabian Deuser
License: UNKNOWN
Platform: UNKNOWN
Classifier: Programming Language :: Python :: 3
Classifier: License :: OSI Approved :: MIT License
Classifier: Operating System :: OS Independent
Requires-Python: >=3.0
License-File: LICENSE
Requires-Dist: torch (>=1.6.0)
